nextup/__main__.py
nextup-0.1.0.dist-info/WHEEL
nextup-0.1.0.dist-info/METADATA
nextup-0.1.0.dist-info/RECORD
